{
  "id": "c8f2f015-8f39-46d0-a49b-6bdc9ddd1cac",
  "prevId": "be96b7f7-8173-43d7-bfe5-8e6ff165572c",
  "version": "7",
  "dialect": "postgresql",
  "tables": {
    "public.caplet_asset_blobs": {
      "name": "caplet_asset_blobs",
      "schema": "",
      "columns": {
        "hash": {
          "name": "hash",
          "type": "text",
          "primaryKey": true,
          "notNull": true
        },
        "size": {
          "name": "size",
          "type": "integer",
          "primaryKey": false,
          "notNull": true
        },
        "payload": {
          "name": "payload",
          "type": "bytea",
          "primaryKey": false,
          "notNull": false
        },
        "object_key": {
          "name": "object_key",
          "type": "text",
          "primaryKey": false,
          "notNull": false
        },
        "verification_status": {
          "name": "verification_status",
          "type": "text",
          "primaryKey": false,
          "notNull": true
        },
        "created_at": {
          "name": "created_at",
          "type": "text",
          "primaryKey": false,
          "notNull": true
        }
      },
      "indexes": {},
      "foreignKeys": {},
      "compositePrimaryKeys": {},
      "uniqueConstraints": {},
      "policies": {},
      "checkConstraints": {},
      "isRLSEnabled": false
    },
    "public.caplet_bundle_entries": {
      "name": "caplet_bundle_entries",
      "schema": "",
      "columns": {
        "revision_key": {
          "name": "revision_key",
          "type": "text",
          "primaryKey": false,
          "notNull": true
        },
        "path": {
          "name": "path",
          "type": "text",
          "primaryKey": false,
          "notNull": true
        },
        "blob_hash": {
          "name": "blob_hash",
          "type": "text",
          "primaryKey": false,
          "notNull": true
        },
        "media_type": {
          "name": "media_type",
          "type": "text",
          "primaryKey": false,
          "notNull": true
        },
        "size": {
          "name": "size",
          "type": "integer",
          "primaryKey": false,
          "notNull": true
        },
        "executable": {
          "name": "executable",
          "type": "boolean",
          "primaryKey": false,
          "notNull": true
        }
      },
      "indexes": {},
      "foreignKeys": {
        "caplet_bundle_entries_revision_key_caplet_revisions_revision_key_fk": {
          "name": "caplet_bundle_entries_revision_key_caplet_revisions_revision_key_fk",
          "tableFrom": "caplet_bundle_entries",
          "tableTo": "caplet_revisions",
          "columnsFrom": ["revision_key"],
          "columnsTo": ["revision_key"],
          "onDelete": "cascade",
          "onUpdate": "no action"
        },
        "caplet_bundle_entries_blob_hash_caplet_asset_blobs_hash_fk": {
          "name": "caplet_bundle_entries_blob_hash_caplet_asset_blobs_hash_fk",
          "tableFrom": "caplet_bundle_entries",
          "tableTo": "caplet_asset_blobs",
          "columnsFrom": ["blob_hash"],
          "columnsTo": ["hash"],
          "onDelete": "no action",
          "onUpdate": "no action"
        }
      },
      "compositePrimaryKeys": {
        "caplet_bundle_entries_revision_key_path_pk": {
          "name": "caplet_bundle_entries_revision_key_path_pk",
          "columns": ["revision_key", "path"]
        }
      },
      "uniqueConstraints": {},
      "policies": {},
      "checkConstraints": {},
      "isRLSEnabled": false
    },
    "public.caplet_installation_observations": {
      "name": "caplet_installation_observations",
      "schema": "",
      "columns": {
        "observation_key": {
          "name": "observation_key",
          "type": "text",
          "primaryKey": true,
          "notNull": true
        },
        "installation_key": {
          "name": "installation_key",
          "type": "text",
          "primaryKey": false,
          "notNull": true
        },
        "resolved_revision": {
          "name": "resolved_revision",
          "type": "text",
          "primaryKey": false,
          "notNull": false
        },
        "content_hash": {
          "name": "content_hash",
          "type": "text",
          "primaryKey": false,
          "notNull": false
        },
        "risk": {
          "name": "risk",
          "type": "jsonb",
          "primaryKey": false,
          "notNull": false
        },
        "status": {
          "name": "status",
          "type": "text",
          "primaryKey": false,
          "notNull": true
        },
        "observed_at": {
          "name": "observed_at",
          "type": "text",
          "primaryKey": false,
          "notNull": true
        }
      },
      "indexes": {
        "caplet_installation_observations_installation_idx": {
          "name": "caplet_installation_observations_installation_idx",
          "columns": [
            {
              "expression": "installation_key",
              "isExpression": false,
              "asc": true,
              "nulls": "last"
            },
            {
              "expression": "observed_at",
              "isExpression": false,
              "asc": true,
              "nulls": "last"
            }
          ],
          "isUnique": false,
          "concurrently": false,
          "method": "btree",
          "with": {}
        }
      },
      "foreignKeys": {
        "caplet_installation_observations_installation_key_caplet_installations_installation_key_fk": {
          "name": "caplet_installation_observations_installation_key_caplet_installations_installation_key_fk",
          "tableFrom": "caplet_installation_observations",
          "tableTo": "caplet_installations",
          "columnsFrom": ["installation_key"],
          "columnsTo": ["installation_key"],
          "onDelete": "cascade",
          "onUpdate": "no action"
        }
      },
      "compositePrimaryKeys": {},
      "uniqueConstraints": {},
      "policies": {},
      "checkConstraints": {},
      "isRLSEnabled": false
    },
    "public.caplet_installations": {
      "name": "caplet_installations",
      "schema": "",
      "columns": {
        "installation_key": {
          "name": "installation_key",
          "type": "text",
          "primaryKey": true,
          "notNull": true
        },
        "record_key": {
          "name": "record_key",
          "type": "text",
          "primaryKey": false,
          "notNull": true
        },
        "generation": {
          "name": "generation",
          "type": "integer",
          "primaryKey": false,
          "notNull": true
        },
        "status": {
          "name": "status",
          "type": "text",
          "primaryKey": false,
          "notNull": true
        },
        "source_kind": {
          "name": "source_kind",
          "type": "text",
          "primaryKey": false,
          "notNull": true
        },
        "source_identity": {
          "name": "source_identity",
          "type": "text",
          "primaryKey": false,
          "notNull": true
        },
        "channel": {
          "name": "channel",
          "type": "text",
          "primaryKey": false,
          "notNull": false
        },
        "created_at": {
          "name": "created_at",
          "type": "text",
          "primaryKey": false,
          "notNull": true
        },
        "updated_at": {
          "name": "updated_at",
          "type": "text",
          "primaryKey": false,
          "notNull": true
        },
        "detached_at": {
          "name": "detached_at",
          "type": "text",
          "primaryKey": false,
          "notNull": false
        },
        "detached_by": {
          "name": "detached_by",
          "type": "text",
          "primaryKey": false,
          "notNull": false
        }
      },
      "indexes": {
        "caplet_installations_record_status_idx": {
          "name": "caplet_installations_record_status_idx",
          "columns": [
            {
              "expression": "record_key",
              "isExpression": false,
              "asc": true,
              "nulls": "last"
            },
            {
              "expression": "status",
              "isExpression": false,
              "asc": true,
              "nulls": "last"
            }
          ],
          "isUnique": false,
          "concurrently": false,
          "method": "btree",
          "with": {}
        },
        "caplet_installations_key_generation_unique": {
          "name": "caplet_installations_key_generation_unique",
          "columns": [
            {
              "expression": "installation_key",
              "isExpression": false,
              "asc": true,
              "nulls": "last"
            },
            {
              "expression": "generation",
              "isExpression": false,
              "asc": true,
              "nulls": "last"
            }
          ],
          "isUnique": true,
          "concurrently": false,
          "method": "btree",
          "with": {}
        }
      },
      "foreignKeys": {
        "caplet_installations_record_key_caplet_records_record_key_fk": {
          "name": "caplet_installations_record_key_caplet_records_record_key_fk",
          "tableFrom": "caplet_installations",
          "tableTo": "caplet_records",
          "columnsFrom": ["record_key"],
          "columnsTo": ["record_key"],
          "onDelete": "cascade",
          "onUpdate": "no action"
        }
      },
      "compositePrimaryKeys": {},
      "uniqueConstraints": {},
      "policies": {},
      "checkConstraints": {},
      "isRLSEnabled": false
    },
    "public.caplet_records": {
      "name": "caplet_records",
      "schema": "",
      "columns": {
        "record_key": {
          "name": "record_key",
          "type": "text",
          "primaryKey": true,
          "notNull": true
        },
        "caplet_id": {
          "name": "caplet_id",
          "type": "text",
          "primaryKey": false,
          "notNull": true
        },
        "current_revision_key": {
          "name": "current_revision_key",
          "type": "text",
          "primaryKey": false,
          "notNull": false
        },
        "head_generation": {
          "name": "head_generation",
          "type": "integer",
          "primaryKey": false,
          "notNull": true
        },
        "history_limit": {
          "name": "history_limit",
          "type": "integer",
          "primaryKey": false,
          "notNull": false
        },
        "created_at": {
          "name": "created_at",
          "type": "text",
          "primaryKey": false,
          "notNull": true
        },
        "updated_at": {
          "name": "updated_at",
          "type": "text",
          "primaryKey": false,
          "notNull": true
        }
      },
      "indexes": {
        "caplet_records_caplet_id_unique": {
          "name": "caplet_records_caplet_id_unique",
          "columns": [
            {
              "expression": "caplet_id",
              "isExpression": false,
              "asc": true,
              "nulls": "last"
            }
          ],
          "isUnique": true,
          "concurrently": false,
          "method": "btree",
          "with": {}
        }
      },
      "foreignKeys": {},
      "compositePrimaryKeys": {},
      "uniqueConstraints": {},
      "policies": {},
      "checkConstraints": {},
      "isRLSEnabled": false
    },
    "public.caplet_revision_backends": {
      "name": "caplet_revision_backends",
      "schema": "",
      "columns": {
        "revision_key": {
          "name": "revision_key",
          "type": "text",
          "primaryKey": false,
          "notNull": true
        },
        "position": {
          "name": "position",
          "type": "integer",
          "primaryKey": false,
          "notNull": true
        },
        "family": {
          "name": "family",
          "type": "text",
          "primaryKey": false,
          "notNull": true
        },
        "child_id": {
          "name": "child_id",
          "type": "text",
          "primaryKey": false,
          "notNull": false
        },
        "config": {
          "name": "config",
          "type": "jsonb",
          "primaryKey": false,
          "notNull": true
        }
      },
      "indexes": {},
      "foreignKeys": {
        "caplet_revision_backends_revision_key_caplet_revisions_revision_key_fk": {
          "name": "caplet_revision_backends_revision_key_caplet_revisions_revision_key_fk",
          "tableFrom": "caplet_revision_backends",
          "tableTo": "caplet_revisions",
          "columnsFrom": ["revision_key"],
          "columnsTo": ["revision_key"],
          "onDelete": "cascade",
          "onUpdate": "no action"
        }
      },
      "compositePrimaryKeys": {
        "caplet_revision_backends_revision_key_position_pk": {
          "name": "caplet_revision_backends_revision_key_position_pk",
          "columns": ["revision_key", "position"]
        }
      },
      "uniqueConstraints": {},
      "policies": {},
      "checkConstraints": {},
      "isRLSEnabled": false
    },
    "public.caplet_revision_tags": {
      "name": "caplet_revision_tags",
      "schema": "",
      "columns": {
        "revision_key": {
          "name": "revision_key",
          "type": "text",
          "primaryKey": false,
          "notNull": true
        },
        "position": {
          "name": "position",
          "type": "integer",
          "primaryKey": false,
          "notNull": true
        },
        "value": {
          "name": "value",
          "type": "text",
          "primaryKey": false,
          "notNull": true
        }
      },
      "indexes": {},
      "foreignKeys": {
        "caplet_revision_tags_revision_key_caplet_revisions_revision_key_fk": {
          "name": "caplet_revision_tags_revision_key_caplet_revisions_revision_key_fk",
          "tableFrom": "caplet_revision_tags",
          "tableTo": "caplet_revisions",
          "columnsFrom": ["revision_key"],
          "columnsTo": ["revision_key"],
          "onDelete": "cascade",
          "onUpdate": "no action"
        }
      },
      "compositePrimaryKeys": {
        "caplet_revision_tags_revision_key_position_pk": {
          "name": "caplet_revision_tags_revision_key_position_pk",
          "columns": ["revision_key", "position"]
        }
      },
      "uniqueConstraints": {},
      "policies": {},
      "checkConstraints": {},
      "isRLSEnabled": false
    },
    "public.caplet_revisions": {
      "name": "caplet_revisions",
      "schema": "",
      "columns": {
        "revision_key": {
          "name": "revision_key",
          "type": "text",
          "primaryKey": true,
          "notNull": true
        },
        "record_key": {
          "name": "record_key",
          "type": "text",
          "primaryKey": false,
          "notNull": true
        },
        "sequence": {
          "name": "sequence",
          "type": "integer",
          "primaryKey": false,
          "notNull": true
        },
        "name": {
          "name": "name",
          "type": "text",
          "primaryKey": false,
          "notNull": true
        },
        "description": {
          "name": "description",
          "type": "text",
          "primaryKey": false,
          "notNull": true
        },
        "body": {
          "name": "body",
          "type": "text",
          "primaryKey": false,
          "notNull": true
        },
        "schema_url": {
          "name": "schema_url",
          "type": "text",
          "primaryKey": false,
          "notNull": false
        },
        "content": {
          "name": "content",
          "type": "jsonb",
          "primaryKey": false,
          "notNull": true
        },
        "content_hash": {
          "name": "content_hash",
          "type": "text",
          "primaryKey": false,
          "notNull": true
        },
        "source_revision": {
          "name": "source_revision",
          "type": "text",
          "primaryKey": false,
          "notNull": false
        },
        "source_content_hash": {
          "name": "source_content_hash",
          "type": "text",
          "primaryKey": false,
          "notNull": false
        },
        "created_at": {
          "name": "created_at",
          "type": "text",
          "primaryKey": false,
          "notNull": true
        },
        "actor": {
          "name": "actor",
          "type": "text",
          "primaryKey": false,
          "notNull": true
        }
      },
      "indexes": {
        "caplet_revisions_record_sequence_unique": {
          "name": "caplet_revisions_record_sequence_unique",
          "columns": [
            {
              "expression": "record_key",
              "isExpression": false,
              "asc": true,
              "nulls": "last"
            },
            {
              "expression": "sequence",
              "isExpression": false,
              "asc": true,
              "nulls": "last"
            }
          ],
          "isUnique": true,
          "concurrently": false,
          "method": "btree",
          "with": {}
        }
      },
      "foreignKeys": {
        "caplet_revisions_record_key_caplet_records_record_key_fk": {
          "name": "caplet_revisions_record_key_caplet_records_record_key_fk",
          "tableFrom": "caplet_revisions",
          "tableTo": "caplet_records",
          "columnsFrom": ["record_key"],
          "columnsTo": ["record_key"],
          "onDelete": "cascade",
          "onUpdate": "no action"
        }
      },
      "compositePrimaryKeys": {},
      "uniqueConstraints": {},
      "policies": {},
      "checkConstraints": {},
      "isRLSEnabled": false
    },
    "public.caplets_schema": {
      "name": "caplets_schema",
      "schema": "",
      "columns": {
        "singleton": {
          "name": "singleton",
          "type": "integer",
          "primaryKey": true,
          "notNull": true
        },
        "version": {
          "name": "version",
          "type": "integer",
          "primaryKey": false,
          "notNull": true
        },
        "applied_at": {
          "name": "applied_at",
          "type": "text",
          "primaryKey": false,
          "notNull": true
        }
      },
      "indexes": {},
      "foreignKeys": {},
      "compositePrimaryKeys": {},
      "uniqueConstraints": {},
      "policies": {},
      "checkConstraints": {},
      "isRLSEnabled": false
    },
    "public.dashboard_sessions": {
      "name": "dashboard_sessions",
      "schema": "",
      "columns": {
        "session_id": {
          "name": "session_id",
          "type": "text",
          "primaryKey": true,
          "notNull": true
        },
        "secret_hash": {
          "name": "secret_hash",
          "type": "text",
          "primaryKey": false,
          "notNull": true
        },
        "operator_client_id": {
          "name": "operator_client_id",
          "type": "text",
          "primaryKey": false,
          "notNull": true
        },
        "role": {
          "name": "role",
          "type": "text",
          "primaryKey": false,
          "notNull": true
        },
        "csrf_token": {
          "name": "csrf_token",
          "type": "text",
          "primaryKey": false,
          "notNull": true
        },
        "created_at": {
          "name": "created_at",
          "type": "text",
          "primaryKey": false,
          "notNull": true
        },
        "expires_at": {
          "name": "expires_at",
          "type": "text",
          "primaryKey": false,
          "notNull": true
        },
        "last_used_at": {
          "name": "last_used_at",
          "type": "text",
          "primaryKey": false,
          "notNull": true
        }
      },
      "indexes": {
        "dashboard_sessions_expires_at_idx": {
          "name": "dashboard_sessions_expires_at_idx",
          "columns": [
            {
              "expression": "expires_at",
              "isExpression": false,
              "asc": true,
              "nulls": "last"
            }
          ],
          "isUnique": false,
          "concurrently": false,
          "method": "btree",
          "with": {}
        },
        "dashboard_sessions_last_used_at_idx": {
          "name": "dashboard_sessions_last_used_at_idx",
          "columns": [
            {
              "expression": "last_used_at",
              "isExpression": false,
              "asc": true,
              "nulls": "last"
            }
          ],
          "isUnique": false,
          "concurrently": false,
          "method": "btree",
          "with": {}
        }
      },
      "foreignKeys": {},
      "compositePrimaryKeys": {},
      "uniqueConstraints": {},
      "policies": {},
      "checkConstraints": {},
      "isRLSEnabled": false
    },
    "public.host_config_generations": {
      "name": "host_config_generations",
      "schema": "",
      "columns": {
        "generation": {
          "name": "generation",
          "type": "integer",
          "primaryKey": true,
          "notNull": true
        },
        "content_hash": {
          "name": "content_hash",
          "type": "text",
          "primaryKey": false,
          "notNull": true
        },
        "created_at": {
          "name": "created_at",
          "type": "text",
          "primaryKey": false,
          "notNull": true
        },
        "created_by": {
          "name": "created_by",
          "type": "text",
          "primaryKey": false,
          "notNull": true
        }
      },
      "indexes": {},
      "foreignKeys": {},
      "compositePrimaryKeys": {},
      "uniqueConstraints": {},
      "policies": {},
      "checkConstraints": {},
      "isRLSEnabled": false
    },
    "public.host_identity": {
      "name": "host_identity",
      "schema": "",
      "columns": {
        "singleton": {
          "name": "singleton",
          "type": "integer",
          "primaryKey": true,
          "notNull": true
        },
        "host_id": {
          "name": "host_id",
          "type": "text",
          "primaryKey": false,
          "notNull": true
        },
        "created_at": {
          "name": "created_at",
          "type": "text",
          "primaryKey": false,
          "notNull": true
        }
      },
      "indexes": {},
      "foreignKeys": {},
      "compositePrimaryKeys": {},
      "uniqueConstraints": {
        "host_identity_host_id_unique": {
          "name": "host_identity_host_id_unique",
          "nullsNotDistinct": false,
          "columns": ["host_id"]
        }
      },
      "policies": {},
      "checkConstraints": {},
      "isRLSEnabled": false
    },
    "public.host_nodes": {
      "name": "host_nodes",
      "schema": "",
      "columns": {
        "node_id": {
          "name": "node_id",
          "type": "text",
          "primaryKey": true,
          "notNull": true
        },
        "started_at": {
          "name": "started_at",
          "type": "text",
          "primaryKey": false,
          "notNull": true
        },
        "heartbeat_at": {
          "name": "heartbeat_at",
          "type": "text",
          "primaryKey": false,
          "notNull": true
        },
        "global_file_manifest": {
          "name": "global_file_manifest",
          "type": "text",
          "primaryKey": false,
          "notNull": true
        },
        "runtime_fingerprint": {
          "name": "runtime_fingerprint",
          "type": "text",
          "primaryKey": false,
          "notNull": true
        },
        "ready": {
          "name": "ready",
          "type": "boolean",
          "primaryKey": false,
          "notNull": true
        }
      },
      "indexes": {},
      "foreignKeys": {},
      "compositePrimaryKeys": {},
      "uniqueConstraints": {},
      "policies": {},
      "checkConstraints": {},
      "isRLSEnabled": false
    },
    "public.host_state_records": {
      "name": "host_state_records",
      "schema": "",
      "columns": {
        "namespace": {
          "name": "namespace",
          "type": "text",
          "primaryKey": false,
          "notNull": true
        },
        "state_key": {
          "name": "state_key",
          "type": "text",
          "primaryKey": false,
          "notNull": true
        },
        "generation": {
          "name": "generation",
          "type": "integer",
          "primaryKey": false,
          "notNull": true
        },
        "payload": {
          "name": "payload",
          "type": "jsonb",
          "primaryKey": false,
          "notNull": true
        },
        "created_at": {
          "name": "created_at",
          "type": "text",
          "primaryKey": false,
          "notNull": true
        },
        "updated_at": {
          "name": "updated_at",
          "type": "text",
          "primaryKey": false,
          "notNull": true
        }
      },
      "indexes": {},
      "foreignKeys": {},
      "compositePrimaryKeys": {
        "host_state_records_namespace_state_key_pk": {
          "name": "host_state_records_namespace_state_key_pk",
          "columns": ["namespace", "state_key"]
        }
      },
      "uniqueConstraints": {},
      "policies": {},
      "checkConstraints": {},
      "isRLSEnabled": false
    },
    "public.maintenance_cursors": {
      "name": "maintenance_cursors",
      "schema": "",
      "columns": {
        "job_name": {
          "name": "job_name",
          "type": "text",
          "primaryKey": true,
          "notNull": true
        },
        "cursor": {
          "name": "cursor",
          "type": "text",
          "primaryKey": false,
          "notNull": false
        },
        "updated_at": {
          "name": "updated_at",
          "type": "text",
          "primaryKey": false,
          "notNull": true
        }
      },
      "indexes": {},
      "foreignKeys": {},
      "compositePrimaryKeys": {},
      "uniqueConstraints": {},
      "policies": {},
      "checkConstraints": {},
      "isRLSEnabled": false
    },
    "public.maintenance_leases": {
      "name": "maintenance_leases",
      "schema": "",
      "columns": {
        "lease_name": {
          "name": "lease_name",
          "type": "text",
          "primaryKey": true,
          "notNull": true
        },
        "owner_node_id": {
          "name": "owner_node_id",
          "type": "text",
          "primaryKey": false,
          "notNull": true
        },
        "fencing_token": {
          "name": "fencing_token",
          "type": "integer",
          "primaryKey": false,
          "notNull": true
        },
        "expires_at": {
          "name": "expires_at",
          "type": "text",
          "primaryKey": false,
          "notNull": true
        },
        "updated_at": {
          "name": "updated_at",
          "type": "text",
          "primaryKey": false,
          "notNull": true
        }
      },
      "indexes": {},
      "foreignKeys": {},
      "compositePrimaryKeys": {},
      "uniqueConstraints": {},
      "policies": {},
      "checkConstraints": {},
      "isRLSEnabled": false
    },
    "public.operator_activity": {
      "name": "operator_activity",
      "schema": "",
      "columns": {
        "activity_key": {
          "name": "activity_key",
          "type": "text",
          "primaryKey": true,
          "notNull": true
        },
        "operator_client_id": {
          "name": "operator_client_id",
          "type": "text",
          "primaryKey": false,
          "notNull": true
        },
        "action": {
          "name": "action",
          "type": "text",
          "primaryKey": false,
          "notNull": true
        },
        "target_kind": {
          "name": "target_kind",
          "type": "text",
          "primaryKey": false,
          "notNull": true
        },
        "target_key": {
          "name": "target_key",
          "type": "text",
          "primaryKey": false,
          "notNull": true
        },
        "outcome": {
          "name": "outcome",
          "type": "text",
          "primaryKey": false,
          "notNull": true
        },
        "metadata": {
          "name": "metadata",
          "type": "jsonb",
          "primaryKey": false,
          "notNull": true
        },
        "created_at": {
          "name": "created_at",
          "type": "text",
          "primaryKey": false,
          "notNull": true
        }
      },
      "indexes": {
        "operator_activity_created_idx": {
          "name": "operator_activity_created_idx",
          "columns": [
            {
              "expression": "created_at",
              "isExpression": false,
              "asc": true,
              "nulls": "last"
            }
          ],
          "isUnique": false,
          "concurrently": false,
          "method": "btree",
          "with": {}
        }
      },
      "foreignKeys": {},
      "compositePrimaryKeys": {},
      "uniqueConstraints": {},
      "policies": {},
      "checkConstraints": {},
      "isRLSEnabled": false
    },
    "public.project_bindings": {
      "name": "project_bindings",
      "schema": "",
      "columns": {
        "binding_id": {
          "name": "binding_id",
          "type": "text",
          "primaryKey": true,
          "notNull": true
        },
        "session_id": {
          "name": "session_id",
          "type": "text",
          "primaryKey": false,
          "notNull": true
        },
        "project_fingerprint": {
          "name": "project_fingerprint",
          "type": "text",
          "primaryKey": false,
          "notNull": true
        },
        "project_root": {
          "name": "project_root",
          "type": "text",
          "primaryKey": false,
          "notNull": true
        },
        "server_project_root": {
          "name": "server_project_root",
          "type": "text",
          "primaryKey": false,
          "notNull": true
        },
        "owner_node_id": {
          "name": "owner_node_id",
          "type": "text",
          "primaryKey": false,
          "notNull": true
        },
        "generation": {
          "name": "generation",
          "type": "integer",
          "primaryKey": false,
          "notNull": true
        },
        "revision": {
          "name": "revision",
          "type": "integer",
          "primaryKey": false,
          "notNull": true
        },
        "state": {
          "name": "state",
          "type": "text",
          "primaryKey": false,
          "notNull": true
        },
        "sync_state": {
          "name": "sync_state",
          "type": "text",
          "primaryKey": false,
          "notNull": true
        },
        "readiness": {
          "name": "readiness",
          "type": "text",
          "primaryKey": false,
          "notNull": true
        },
        "active": {
          "name": "active",
          "type": "boolean",
          "primaryKey": false,
          "notNull": true
        },
        "last_heartbeat_at": {
          "name": "last_heartbeat_at",
          "type": "text",
          "primaryKey": false,
          "notNull": true
        },
        "expires_at": {
          "name": "expires_at",
          "type": "text",
          "primaryKey": false,
          "notNull": true
        },
        "quarantined_at": {
          "name": "quarantined_at",
          "type": "text",
          "primaryKey": false,
          "notNull": false
        },
        "quarantine_reason": {
          "name": "quarantine_reason",
          "type": "text",
          "primaryKey": false,
          "notNull": false
        },
        "created_at": {
          "name": "created_at",
          "type": "text",
          "primaryKey": false,
          "notNull": true
        },
        "updated_at": {
          "name": "updated_at",
          "type": "text",
          "primaryKey": false,
          "notNull": true
        }
      },
      "indexes": {
        "project_bindings_owner_expiry_idx": {
          "name": "project_bindings_owner_expiry_idx",
          "columns": [
            {
              "expression": "owner_node_id",
              "isExpression": false,
              "asc": true,
              "nulls": "last"
            },
            {
              "expression": "expires_at",
              "isExpression": false,
              "asc": true,
              "nulls": "last"
            }
          ],
          "isUnique": false,
          "concurrently": false,
          "method": "btree",
          "with": {}
        },
        "project_bindings_active_expiry_idx": {
          "name": "project_bindings_active_expiry_idx",
          "columns": [
            {
              "expression": "active",
              "isExpression": false,
              "asc": true,
              "nulls": "last"
            },
            {
              "expression": "expires_at",
              "isExpression": false,
              "asc": true,
              "nulls": "last"
            }
          ],
          "isUnique": false,
          "concurrently": false,
          "method": "btree",
          "with": {}
        }
      },
      "foreignKeys": {},
      "compositePrimaryKeys": {},
      "uniqueConstraints": {},
      "policies": {},
      "checkConstraints": {},
      "isRLSEnabled": false
    },
    "public.remote_client_superseded_refresh_tokens": {
      "name": "remote_client_superseded_refresh_tokens",
      "schema": "",
      "columns": {
        "family_id": {
          "name": "family_id",
          "type": "text",
          "primaryKey": false,
          "notNull": true
        },
        "token_hash": {
          "name": "token_hash",
          "type": "text",
          "primaryKey": false,
          "notNull": true
        },
        "superseded_at": {
          "name": "superseded_at",
          "type": "text",
          "primaryKey": false,
          "notNull": true
        }
      },
      "indexes": {
        "remote_client_superseded_refresh_hash_unique": {
          "name": "remote_client_superseded_refresh_hash_unique",
          "columns": [
            {
              "expression": "token_hash",
              "isExpression": false,
              "asc": true,
              "nulls": "last"
            }
          ],
          "isUnique": true,
          "concurrently": false,
          "method": "btree",
          "with": {}
        }
      },
      "foreignKeys": {
        "remote_client_superseded_refresh_tokens_family_id_remote_client_token_families_family_id_fk": {
          "name": "remote_client_superseded_refresh_tokens_family_id_remote_client_token_families_family_id_fk",
          "tableFrom": "remote_client_superseded_refresh_tokens",
          "tableTo": "remote_client_token_families",
          "columnsFrom": ["family_id"],
          "columnsTo": ["family_id"],
          "onDelete": "cascade",
          "onUpdate": "no action"
        }
      },
      "compositePrimaryKeys": {
        "remote_client_superseded_refresh_tokens_family_id_token_hash_pk": {
          "name": "remote_client_superseded_refresh_tokens_family_id_token_hash_pk",
          "columns": ["family_id", "token_hash"]
        }
      },
      "uniqueConstraints": {},
      "policies": {},
      "checkConstraints": {},
      "isRLSEnabled": false
    },
    "public.remote_client_token_families": {
      "name": "remote_client_token_families",
      "schema": "",
      "columns": {
        "family_id": {
          "name": "family_id",
          "type": "text",
          "primaryKey": true,
          "notNull": true
        },
        "client_id": {
          "name": "client_id",
          "type": "text",
          "primaryKey": false,
          "notNull": true
        },
        "refresh_token_hash": {
          "name": "refresh_token_hash",
          "type": "text",
          "primaryKey": false,
          "notNull": true
        },
        "created_at": {
          "name": "created_at",
          "type": "text",
          "primaryKey": false,
          "notNull": true
        },
        "revoked_at": {
          "name": "revoked_at",
          "type": "text",
          "primaryKey": false,
          "notNull": false
        }
      },
      "indexes": {
        "remote_client_token_families_client_unique": {
          "name": "remote_client_token_families_client_unique",
          "columns": [
            {
              "expression": "client_id",
              "isExpression": false,
              "asc": true,
              "nulls": "last"
            }
          ],
          "isUnique": true,
          "concurrently": false,
          "method": "btree",
          "with": {}
        },
        "remote_client_token_families_refresh_hash_unique": {
          "name": "remote_client_token_families_refresh_hash_unique",
          "columns": [
            {
              "expression": "refresh_token_hash",
              "isExpression": false,
              "asc": true,
              "nulls": "last"
            }
          ],
          "isUnique": true,
          "concurrently": false,
          "method": "btree",
          "with": {}
        }
      },
      "foreignKeys": {
        "remote_client_token_families_client_id_remote_clients_client_id_fk": {
          "name": "remote_client_token_families_client_id_remote_clients_client_id_fk",
          "tableFrom": "remote_client_token_families",
          "tableTo": "remote_clients",
          "columnsFrom": ["client_id"],
          "columnsTo": ["client_id"],
          "onDelete": "cascade",
          "onUpdate": "no action"
        }
      },
      "compositePrimaryKeys": {},
      "uniqueConstraints": {},
      "policies": {},
      "checkConstraints": {},
      "isRLSEnabled": false
    },
    "public.remote_clients": {
      "name": "remote_clients",
      "schema": "",
      "columns": {
        "client_id": {
          "name": "client_id",
          "type": "text",
          "primaryKey": true,
          "notNull": true
        },
        "client_label": {
          "name": "client_label",
          "type": "text",
          "primaryKey": false,
          "notNull": true
        },
        "role": {
          "name": "role",
          "type": "text",
          "primaryKey": false,
          "notNull": true
        },
        "host_url": {
          "name": "host_url",
          "type": "text",
          "primaryKey": false,
          "notNull": true
        },
        "access_token_hash": {
          "name": "access_token_hash",
          "type": "text",
          "primaryKey": false,
          "notNull": true
        },
        "access_expires_at": {
          "name": "access_expires_at",
          "type": "text",
          "primaryKey": false,
          "notNull": true
        },
        "created_at": {
          "name": "created_at",
          "type": "text",
          "primaryKey": false,
          "notNull": true
        },
        "last_used_at": {
          "name": "last_used_at",
          "type": "text",
          "primaryKey": false,
          "notNull": false
        },
        "revoked_at": {
          "name": "revoked_at",
          "type": "text",
          "primaryKey": false,
          "notNull": false
        }
      },
      "indexes": {
        "remote_clients_access_token_hash_unique": {
          "name": "remote_clients_access_token_hash_unique",
          "columns": [
            {
              "expression": "access_token_hash",
              "isExpression": false,
              "asc": true,
              "nulls": "last"
            }
          ],
          "isUnique": true,
          "concurrently": false,
          "method": "btree",
          "with": {}
        }
      },
      "foreignKeys": {},
      "compositePrimaryKeys": {},
      "uniqueConstraints": {},
      "policies": {},
      "checkConstraints": {},
      "isRLSEnabled": false
    },
    "public.remote_pairing_codes": {
      "name": "remote_pairing_codes",
      "schema": "",
      "columns": {
        "code_id": {
          "name": "code_id",
          "type": "text",
          "primaryKey": true,
          "notNull": true
        },
        "host_url": {
          "name": "host_url",
          "type": "text",
          "primaryKey": false,
          "notNull": true
        },
        "secret_hash": {
          "name": "secret_hash",
          "type": "text",
          "primaryKey": false,
          "notNull": true
        },
        "client_label": {
          "name": "client_label",
          "type": "text",
          "primaryKey": false,
          "notNull": false
        },
        "created_at": {
          "name": "created_at",
          "type": "text",
          "primaryKey": false,
          "notNull": true
        },
        "expires_at": {
          "name": "expires_at",
          "type": "text",
          "primaryKey": false,
          "notNull": true
        },
        "attempts": {
          "name": "attempts",
          "type": "integer",
          "primaryKey": false,
          "notNull": true
        },
        "max_attempts": {
          "name": "max_attempts",
          "type": "integer",
          "primaryKey": false,
          "notNull": true
        },
        "used_at": {
          "name": "used_at",
          "type": "text",
          "primaryKey": false,
          "notNull": false
        }
      },
      "indexes": {},
      "foreignKeys": {},
      "compositePrimaryKeys": {},
      "uniqueConstraints": {},
      "policies": {},
      "checkConstraints": {},
      "isRLSEnabled": false
    },
    "public.remote_pending_logins": {
      "name": "remote_pending_logins",
      "schema": "",
      "columns": {
        "flow_id": {
          "name": "flow_id",
          "type": "text",
          "primaryKey": true,
          "notNull": true
        },
        "host_url": {
          "name": "host_url",
          "type": "text",
          "primaryKey": false,
          "notNull": true
        },
        "host_identity": {
          "name": "host_identity",
          "type": "text",
          "primaryKey": false,
          "notNull": false
        },
        "operator_code_hash": {
          "name": "operator_code_hash",
          "type": "text",
          "primaryKey": false,
          "notNull": true
        },
        "pending_refresh_hash": {
          "name": "pending_refresh_hash",
          "type": "text",
          "primaryKey": false,
          "notNull": true
        },
        "pending_refresh_replay": {
          "name": "pending_refresh_replay",
          "type": "jsonb",
          "primaryKey": false,
          "notNull": false
        },
        "pending_completion_hash": {
          "name": "pending_completion_hash",
          "type": "text",
          "primaryKey": false,
          "notNull": true
        },
        "completion_replay": {
          "name": "completion_replay",
          "type": "jsonb",
          "primaryKey": false,
          "notNull": false
        },
        "client_label": {
          "name": "client_label",
          "type": "text",
          "primaryKey": false,
          "notNull": true
        },
        "requested_role": {
          "name": "requested_role",
          "type": "text",
          "primaryKey": false,
          "notNull": true
        },
        "granted_role": {
          "name": "granted_role",
          "type": "text",
          "primaryKey": false,
          "notNull": false
        },
        "client_fingerprint": {
          "name": "client_fingerprint",
          "type": "text",
          "primaryKey": false,
          "notNull": false
        },
        "source_hint": {
          "name": "source_hint",
          "type": "text",
          "primaryKey": false,
          "notNull": false
        },
        "created_at": {
          "name": "created_at",
          "type": "text",
          "primaryKey": false,
          "notNull": true
        },
        "code_expires_at": {
          "name": "code_expires_at",
          "type": "text",
          "primaryKey": false,
          "notNull": true
        },
        "flow_expires_at": {
          "name": "flow_expires_at",
          "type": "text",
          "primaryKey": false,
          "notNull": true
        },
        "status": {
          "name": "status",
          "type": "text",
          "primaryKey": false,
          "notNull": true
        },
        "operator_code_fingerprint": {
          "name": "operator_code_fingerprint",
          "type": "text",
          "primaryKey": false,
          "notNull": false
        },
        "approved_at": {
          "name": "approved_at",
          "type": "text",
          "primaryKey": false,
          "notNull": false
        },
        "denied_at": {
          "name": "denied_at",
          "type": "text",
          "primaryKey": false,
          "notNull": false
        },
        "cancelled_at": {
          "name": "cancelled_at",
          "type": "text",
          "primaryKey": false,
          "notNull": false
        },
        "exchanged_at": {
          "name": "exchanged_at",
          "type": "text",
          "primaryKey": false,
          "notNull": false
        }
      },
      "indexes": {
        "remote_pending_logins_operator_code_hash_unique": {
          "name": "remote_pending_logins_operator_code_hash_unique",
          "columns": [
            {
              "expression": "operator_code_hash",
              "isExpression": false,
              "asc": true,
              "nulls": "last"
            }
          ],
          "isUnique": true,
          "concurrently": false,
          "method": "btree",
          "with": {}
        },
        "remote_pending_logins_refresh_hash_unique": {
          "name": "remote_pending_logins_refresh_hash_unique",
          "columns": [
            {
              "expression": "pending_refresh_hash",
              "isExpression": false,
              "asc": true,
              "nulls": "last"
            }
          ],
          "isUnique": true,
          "concurrently": false,
          "method": "btree",
          "with": {}
        },
        "remote_pending_logins_completion_hash_unique": {
          "name": "remote_pending_logins_completion_hash_unique",
          "columns": [
            {
              "expression": "pending_completion_hash",
              "isExpression": false,
              "asc": true,
              "nulls": "last"
            }
          ],
          "isUnique": true,
          "concurrently": false,
          "method": "btree",
          "with": {}
        }
      },
      "foreignKeys": {},
      "compositePrimaryKeys": {},
      "uniqueConstraints": {},
      "policies": {},
      "checkConstraints": {},
      "isRLSEnabled": false
    },
    "public.remote_pending_superseded_refresh_tokens": {
      "name": "remote_pending_superseded_refresh_tokens",
      "schema": "",
      "columns": {
        "flow_id": {
          "name": "flow_id",
          "type": "text",
          "primaryKey": false,
          "notNull": true
        },
        "token_hash": {
          "name": "token_hash",
          "type": "text",
          "primaryKey": false,
          "notNull": true
        },
        "superseded_at": {
          "name": "superseded_at",
          "type": "text",
          "primaryKey": false,
          "notNull": true
        }
      },
      "indexes": {
        "remote_pending_superseded_refresh_hash_unique": {
          "name": "remote_pending_superseded_refresh_hash_unique",
          "columns": [
            {
              "expression": "token_hash",
              "isExpression": false,
              "asc": true,
              "nulls": "last"
            }
          ],
          "isUnique": true,
          "concurrently": false,
          "method": "btree",
          "with": {}
        }
      },
      "foreignKeys": {
        "remote_pending_superseded_refresh_tokens_flow_id_remote_pending_logins_flow_id_fk": {
          "name": "remote_pending_superseded_refresh_tokens_flow_id_remote_pending_logins_flow_id_fk",
          "tableFrom": "remote_pending_superseded_refresh_tokens",
          "tableTo": "remote_pending_logins",
          "columnsFrom": ["flow_id"],
          "columnsTo": ["flow_id"],
          "onDelete": "cascade",
          "onUpdate": "no action"
        }
      },
      "compositePrimaryKeys": {
        "remote_pending_superseded_refresh_tokens_flow_id_token_hash_pk": {
          "name": "remote_pending_superseded_refresh_tokens_flow_id_token_hash_pk",
          "columns": ["flow_id", "token_hash"]
        }
      },
      "uniqueConstraints": {},
      "policies": {},
      "checkConstraints": {},
      "isRLSEnabled": false
    },
    "public.setup_approvals": {
      "name": "setup_approvals",
      "schema": "",
      "columns": {
        "project_fingerprint": {
          "name": "project_fingerprint",
          "type": "text",
          "primaryKey": false,
          "notNull": true
        },
        "caplet_id": {
          "name": "caplet_id",
          "type": "text",
          "primaryKey": false,
          "notNull": true
        },
        "content_hash": {
          "name": "content_hash",
          "type": "text",
          "primaryKey": false,
          "notNull": true
        },
        "target_kind": {
          "name": "target_kind",
          "type": "text",
          "primaryKey": false,
          "notNull": true
        },
        "generation": {
          "name": "generation",
          "type": "integer",
          "primaryKey": false,
          "notNull": true
        },
        "payload": {
          "name": "payload",
          "type": "jsonb",
          "primaryKey": false,
          "notNull": true
        },
        "approved_at": {
          "name": "approved_at",
          "type": "text",
          "primaryKey": false,
          "notNull": true
        },
        "actor": {
          "name": "actor",
          "type": "text",
          "primaryKey": false,
          "notNull": true
        },
        "created_at": {
          "name": "created_at",
          "type": "text",
          "primaryKey": false,
          "notNull": true
        },
        "updated_at": {
          "name": "updated_at",
          "type": "text",
          "primaryKey": false,
          "notNull": true
        }
      },
      "indexes": {},
      "foreignKeys": {},
      "compositePrimaryKeys": {
        "setup_approvals_project_fingerprint_caplet_id_content_hash_target_kind_pk": {
          "name": "setup_approvals_project_fingerprint_caplet_id_content_hash_target_kind_pk",
          "columns": ["project_fingerprint", "caplet_id", "content_hash", "target_kind"]
        }
      },
      "uniqueConstraints": {},
      "policies": {},
      "checkConstraints": {},
      "isRLSEnabled": false
    },
    "public.setup_attempt_sets": {
      "name": "setup_attempt_sets",
      "schema": "",
      "columns": {
        "project_fingerprint": {
          "name": "project_fingerprint",
          "type": "text",
          "primaryKey": false,
          "notNull": true
        },
        "caplet_id": {
          "name": "caplet_id",
          "type": "text",
          "primaryKey": false,
          "notNull": true
        },
        "generation": {
          "name": "generation",
          "type": "integer",
          "primaryKey": false,
          "notNull": true
        },
        "payload": {
          "name": "payload",
          "type": "jsonb",
          "primaryKey": false,
          "notNull": true
        },
        "created_at": {
          "name": "created_at",
          "type": "text",
          "primaryKey": false,
          "notNull": true
        },
        "updated_at": {
          "name": "updated_at",
          "type": "text",
          "primaryKey": false,
          "notNull": true
        }
      },
      "indexes": {},
      "foreignKeys": {},
      "compositePrimaryKeys": {
        "setup_attempt_sets_project_fingerprint_caplet_id_pk": {
          "name": "setup_attempt_sets_project_fingerprint_caplet_id_pk",
          "columns": ["project_fingerprint", "caplet_id"]
        }
      },
      "uniqueConstraints": {},
      "policies": {},
      "checkConstraints": {},
      "isRLSEnabled": false
    },
    "public.vault_access_grants": {
      "name": "vault_access_grants",
      "schema": "",
      "columns": {
        "subject_kind": {
          "name": "subject_kind",
          "type": "text",
          "primaryKey": false,
          "notNull": true
        },
        "subject_key": {
          "name": "subject_key",
          "type": "text",
          "primaryKey": false,
          "notNull": true
        },
        "record_key": {
          "name": "record_key",
          "type": "text",
          "primaryKey": false,
          "notNull": false
        },
        "caplet_id": {
          "name": "caplet_id",
          "type": "text",
          "primaryKey": false,
          "notNull": false
        },
        "vault_key": {
          "name": "vault_key",
          "type": "text",
          "primaryKey": false,
          "notNull": true
        },
        "reference_name": {
          "name": "reference_name",
          "type": "text",
          "primaryKey": false,
          "notNull": true
        },
        "origin_kind": {
          "name": "origin_kind",
          "type": "text",
          "primaryKey": false,
          "notNull": true
        },
        "origin_path": {
          "name": "origin_path",
          "type": "text",
          "primaryKey": false,
          "notNull": false
        },
        "created_at": {
          "name": "created_at",
          "type": "text",
          "primaryKey": false,
          "notNull": true
        },
        "created_by": {
          "name": "created_by",
          "type": "text",
          "primaryKey": false,
          "notNull": true
        }
      },
      "indexes": {},
      "foreignKeys": {
        "vault_access_grants_record_key_caplet_records_record_key_fk": {
          "name": "vault_access_grants_record_key_caplet_records_record_key_fk",
          "tableFrom": "vault_access_grants",
          "tableTo": "caplet_records",
          "columnsFrom": ["record_key"],
          "columnsTo": ["record_key"],
          "onDelete": "cascade",
          "onUpdate": "no action"
        }
      },
      "compositePrimaryKeys": {
        "vault_access_grants_subject_kind_subject_key_reference_name_pk": {
          "name": "vault_access_grants_subject_kind_subject_key_reference_name_pk",
          "columns": ["subject_kind", "subject_key", "reference_name"]
        }
      },
      "uniqueConstraints": {},
      "policies": {},
      "checkConstraints": {},
      "isRLSEnabled": false
    }
  },
  "enums": {},
  "schemas": {},
  "sequences": {},
  "roles": {},
  "policies": {},
  "views": {},
  "_meta": {
    "columns": {},
    "schemas": {},
    "tables": {}
  }
}
